[
  {
    "name": "Aether Legacy",
    "status": "wip",
    "repo": "Dokucraft/Mod-Support-Aether-Legacy",
    "packs": [
      {
        "versions": [ "1.12.2" ],
        "flavor": "light",
        "branch": "1.12.2"
      }
    ]
  },
  {
    "name": "Applied Energistics 2",
    "status": "wip",
    "repo": "Dokucraft/Mod-Support-Applied-Energistics",
    "packs": [
      {
        "versions": [ "1.12.2" ],
        "flavor": "light",
        "branch": "1.12.2"
      },
      {
        "versions": [ "1.18.2" ],
        "flavor": "light",
        "branch": "1.18.2"
      }
    ]
  },
  {
    "name": "Artifacts",
    "status": "wip",
    "repo": "Dokucraft/Mod-Support-Artifacts",
    "packs": [
      {
        "versions": [ "1.20.1" ],
        "flavor": "light",
        "branch": "main"
      }
    ]
  },
  {
    "name": "Caves and Cliffs",
    "status": "completed",
    "repo": "Dokucraft/Mod-Support-Caves-and-Cliffs",
    "packs": [
      {
        "versions": [ "1.16.5" ],
        "flavor": "light",
        "branch": "Light-1.16.5"
      },
      {
        "versions": [ "1.16.5" ],
        "flavor": "high",
        "branch": "High-1.16.5"
      }
    ]
  },
  {
    "name": "CC:Tweaked",
    "status": "completed",
    "repo": "Dokucraft/Mod-Support-CC-Tweaked",
    "packs": [
      {
        "versions": [ "1.16.4", "1.16.5", "1.17.1", "1.18.1", "1.18.2", "1.19.2", "1.19.3", "1.19.4", "1.20", "1.20.1" ],
        "flavor": "light",
        "branch": "latest"
      }
    ]
  },
  {
    "name": "Create",
    "status": "completed",
    "repo": "Dokucraft/Mod-Support-Create-Mod",
    "packs": [
      {
        "versions": [ "1.18.2", "1.19.2" ],
        "flavor": "light",
        "branch": "main"
      }
    ]
  },
  {
    "name": "Curios",
    "status": "wip",
    "repo": "Dokucraft/Mod-Support-Curios",
    "packs": [
      {
        "versions": [ "1.20.1" ],
        "flavor": "light",
        "branch": "main"
      }
    ]
  },
  {
    "name": "Decorative Blocks",
    "status": "completed",
    "repo": "Dokucraft/Mod-Support-Decorative-Blocks",
    "packs": [
      {
        "versions": [ "1.18.2" ],
        "flavor": "light",
        "branch": "main"
      }
    ]
  },
  {
    "name": "Disenchanting Forge",
    "status": "wip",
    "repo": "Dokucraft/Mod-Support-Disenchanting-Forge",
    "packs": [
      {
        "versions": [ "1.20.1" ],
        "flavor": "light",
        "branch": "main"
      }
    ]
  },
  {
    "name": "Extreme Reactors",
    "status": "completed",
    "repo": "Dokucraft/Mod-Support-Extreme-Reactors",
    "packs": [
      {
        "versions": [ "1.12.2" ],
        "flavor": "light",
        "branch": "1.12.2"
      },
      {
        "versions": [ "1.20.1" ],
        "flavor": "light",
        "branch": "1.20.1"
      }
    ]
  },
  {
    "name": "Extreme Sound Muffler",
    "status": "completed",
    "repo": "Dokucraft/Mod-Support-Extreme-Sound-Muffler",
    "packs": [
      {
        "versions": [ "1.20.1" ],
        "flavor": "light",
        "branch": "main"
      }
    ]
  },
  {
    "name": "Farmer's Delight",
    "status": "completed",
    "repo": "Dokucraft/Mod-Support-Farmers-Delight",
    "packs": [
      {
        "versions": [ "1.18.2", "1.19.2" ],
        "flavor": "light",
        "branch": "main"
      }
    ]
  },
  {
    "name": "Framed Blocks",
    "status": "wip",
    "repo": "Dokucraft/Mod-Support-Framed-Blocks",
    "packs": [
      {
        "versions": [ "1.20.1" ],
        "flavor": "light",
        "branch": "main"
      }
    ]
  },
  {
    "name": "Fusion",
    "status": "wip",
    "repo": "Dokucraft/Mod-Support-Fusion",
    "packs": [
      {
        "versions": [ "1.20.1" ],
        "flavor": "light",
        "branch": "main"
      }
    ]
  },
  {
    "name": "Guard Villagers",
    "status": "wip",
    "repo": "Dokucraft/Mod-Support-Guard-Villagers",
    "packs": [
      {
        "versions": [ "1.20.1" ],
        "flavor": "light",
        "branch": "main"
      }
    ]
  },
  {
    "name": "Iron Chests",
    "status": "completed",
    "repo": "Dokucraft/Mod-Support-Iron-Chests",
    "packs": [
      {
        "versions": [ "1.18.2" ],
        "flavor": "light",
        "branch": "1.18.2"
      }
    ]
  },
  {
    "name": "Iron Furnaces",
    "status": "completed",
    "repo": "Dokucraft/Mod-Support-Iron-Furnaces",
    "packs": [
      {
        "versions": [ "1.18.2" ],
        "flavor": "light",
        "branch": "1.18.2"
      }
    ]
  },
  {
    "name": "Just Enough Items",
    "status": "completed",
    "repo": "Dokucraft/Mod-Support-Just-Enough-Items",
    "packs": [
      {
        "versions": [ "1.18.2" ],
        "flavor": "light",
        "branch": "1.18.2"
      },
      {
        "versions": [ "1.20.1" ],
        "flavor": "light",
        "branch": "1.20.1"
      }
    ]
  },
  {
    "name": "Mekanism",
    "status": "wip",
    "repo": "Dokucraft/Mod-Support-Mekanism",
    "packs": [
      {
        "versions": [ "1.12.2" ],
        "flavor": "light",
        "branch": "1.12.2"
      },
      {
        "versions": [ "1.18.2", "1.19.2", "1.20.1" ],
        "flavor": "light",
        "branch": "latest"
      }
    ]
  },
  {
    "name": "Miner's Delight",
    "status": "completed",
    "repo": "Dokucraft/Mod-Support-Miners-Delight",
    "packs": [
      {
        "versions": [ "1.18.2", "1.19.2" ],
        "flavor": "light",
        "branch": "main"
      }
    ]
  },
  {
    "name": "Nether's Delight",
    "status": "wip",
    "repo": "Dokucraft/Mod-Support-Nethers-Delight",
    "packs": [
      {
        "versions": [ "1.18.2", "1.19.2" ],
        "flavor": "light",
        "branch": "main"
      }
    ]
  },
  {
    "name": "ProjectE",
    "status": "wip",
    "repo": "Dokucraft/Mod-Support-ProjectE",
    "packs": [
      {
        "versions": [ "1.16.5", "1.18.1", "1.18.2", "1.19.2" ],
        "flavor": "light",
        "branch": "latest"
      }
    ]
  },
  {
    "name": "Quark",
    "status": "wip",
    "repo": "Dokucraft/Mod-Support-Quark",
    "packs": [
      {
        "versions": [ "1.16.5" ],
        "flavor": "light",
        "branch": "1.16.5"
      }
    ]
  },
  {
    "name": "Railcraft",
    "status": "wip",
    "repo": "Dokucraft/Mod-Support-Railcraft",
    "packs": [
      {
        "versions": [ "1.20.1" ],
        "flavor": "light",
        "branch": "main"
      }
    ]
  },
  {
    "name": "Rechiseled",
    "status": "wip",
    "repo": "Dokucraft/Mod-Support-Rechiseled",
    "packs": [
      {
        "versions": [ "1.20.1" ],
        "flavor": "light",
        "branch": "main"
      }
    ]
  },
  {
    "name": "Roughly Enough Items",
    "status": "completed",
    "repo": "Dokucraft/Mod-Support-Roughly-Enough-Items",
    "packs": [
      {
        "versions": [ "1.18.2" ],
        "flavor": "light",
        "branch": "1.18.2"
      }
    ]
  },
  {
    "name": "Storage Drawers",
    "status": "wip",
    "repo": "Dokucraft/Mod-Support-Storage-Drawers",
    "packs": [
      {
        "versions": [ "1.20.1" ],
        "flavor": "light",
        "branch": "main"
      }
    ]
  },
  {
    "name": "Thermal Mods",
    "status": "wip",
    "repo": "Dokucraft/Mod-Support-Thermal",
    "packs": [
      {
        "versions": [ "1.12.2" ],
        "flavor": "light",
        "branch": "1.12.2"
      },
      {
        "versions": [ "1.18.2" ],
        "flavor": "light",
        "branch": "1.18.2"
      }
    ]
  },
  {
    "name": "Tinkers Construct",
    "status": "wip",
    "repo": "Dokucraft/Mod-Support-Tinkers-Construct",
    "packs": [
      {
        "versions": [ "1.12.2" ],
        "flavor": "light",
        "branch": "1.12.2"
      },
      {
        "versions": [ "1.18.2" ],
        "flavor": "light",
        "branch": "1.18.2"
      }
    ]
  }
]
